moments/server.py
moments/wechat.scpt
mcp_wechat_moments-0.0.5.dist-info/METADATA
mcp_wechat_moments-0.0.5.dist-info/WHEEL
mcp_wechat_moments-0.0.5.dist-info/entry_points.txt
mcp_wechat_moments-0.0.5.dist-info/top_level.txt
mcp_wechat_moments-0.0.5.dist-info/RECORD
