Metadata-Version: 2.2
Name: mcp-wechat-moments
Version: 0.0.5
Summary: MCP server for publish wechat moments
Author-email: Gemini Wen <coffeesherk@gmail.com>
Requires-Python: >=3.11
Requires-Dist: mcp
